{"assets":{"BC61442EF858D1B1100978DBB6B7004F":{"type":"texture","index":204,"assetRequest":{"type":"slide","state":"outgoing","slide":"B1224CA4-77F9-49EB-AF59-1F6C4BF85D3D"},"url":{"web":"assets/BC61442EF858D1B1100978DBB6B7004F.svg"},"width":1024,"height":768},"394F45113F5805CC2E5FA74100160B86":{"type":"texture","index":205,"assetRequest":{"type":"slide","state":"incoming","slide":"5987FE44-8296-40A6-9E72-C982B9003CA7"},"url":{"web":"assets/394F45113F5805CC2E5FA74100160B86.svg"},"width":1024,"height":768}},"events":[{"effects":[{"beginTime":0,"baseLayer":{"animations":[],"initialState":{"affineTransform":[1,0,0,1,0,0],"masksToBounds":false,"rotation":0,"scale":1,"position":{"pointX":512,"pointY":384},"width":1024,"sublayerTransform":[1,0,0,0,0,1,0,0,0,0,1,0,0,0,0,1],"contentsRect":{"y":0,"x":0,"width":1,"height":1},"opacity":1,"edgeAntialiasingMask":251658240,"height":768,"hidden":false,"anchorPoint":{"pointX":0.5,"pointY":0.5}},"objectID":"0","layers":[{"animations":[],"initialState":{"affineTransform":[1,0,0,1,0,0],"masksToBounds":false,"rotation":0,"scale":1,"position":{"pointX":512,"pointY":384},"width":1024,"sublayerTransform":[1,0,0,0,0,1,0,0,0,0,1,-0.0004922987690640373,0,0,0,1],"contentsRect":{"y":0,"x":0,"width":1,"height":1},"opacity":1,"edgeAntialiasingMask":251658240,"height":768,"hidden":false,"anchorPoint":{"pointX":0.5,"pointY":0.5}},"layers":[{"animations":[],"layers":[],"initialState":{"affineTransform":[1,0,0,1,0,0],"masksToBounds":false,"rotation":0,"scale":1,"position":{"pointX":512,"pointY":384},"width":1024,"sublayerTransform":[1,0,0,0,0,1,0,0,0,0,1,0,0,0,0,1],"contentsRect":{"y":0,"x":0,"width":1,"height":1},"opacity":1,"edgeAntialiasingMask":0,"height":768,"hidden":false,"anchorPoint":{"pointX":0.5,"pointY":0.5}},"texture":"394F45113F5805CC2E5FA74100160B86"},{"animations":[{"timeOffset":0,"from":{"scalar":false},"beginTime":0,"repeatCount":0,"fillMode":"both","property":"hidden","autoreverses":false,"duration":0.01,"to":{"scalar":true}}],"layers":[],"initialState":{"affineTransform":[1,0,0,1,0,0],"masksToBounds":false,"rotation":0,"scale":1,"position":{"pointX":512,"pointY":384},"width":1024,"sublayerTransform":[1,0,0,0,0,1,0,0,0,0,1,0,0,0,0,1],"contentsRect":{"y":0,"x":0,"width":1,"height":1},"opacity":1,"edgeAntialiasingMask":0,"height":768,"hidden":false,"anchorPoint":{"pointX":0.5,"pointY":0.5}},"texture":"BC61442EF858D1B1100978DBB6B7004F"}]}]},"effects":[],"duration":0.01,"type":"transition","name":"none","objectID":"0"}],"automaticPlay":false,"hyperlinks":[],"accessibility":[{"text":"References","targetRectangle":{"y":68,"x":209,"width":212.856,"height":57}},{"text":"HY_mLC05_txt__L_3L_V4__CMYK.pdf","targetRectangle":{"y":677,"x":24,"width":200.0000152587891,"height":68.71165466308594}},{"text":"￼","targetRectangle":{"y":720,"x":972.5,"width":14,"height":16}},{"text":"basic_FoS_flame_logo.pdf","targetRectangle":{"y":-5,"x":-7,"width":215,"height":203.0555572509766}},{"text":"www.helsinki.fi/yliopisto","targetRectangle":{"y":720,"x":611,"width":136.28125,"height":16}},{"text":"Allen, J., & Beaumont, C. (2015). Continental margin syn‐rift salt tectonics at intermediate width margins. Basin Research.","targetRectangle":{"y":186,"x":209,"width":726.4453125,"height":18.29296875}},{"text":"Allken, V., Huismans, R. S., Fossen, H., & Thieulot, C. (2013). 3D numerical modelling of graben interaction and linkage: a case study of the Canyonlands grabens, Utah. Basin Research, 25(4), 436-449.","targetRectangle":{"y":204.29296875,"x":209,"width":783.0615234375,"height":34.00732421875}},{"text":"Braun, J., & Yamato, P. (2010). Structural evolution of a three-dimensional, finite-width crustal wedge. Tectonophysics, 484(1), 181-192.","targetRectangle":{"y":238.30029296875,"x":209,"width":737.197265625,"height":34.00732421875}},{"text":"Butler, J. P., Beaumont, C., & Jamieson, R. A. (2013). The Alps 1: A working geodynamic model for burial and exhumation of (ultra) high-pressure rocks in Alpine-type orogens. Earth and Planetary Science Letters, 377, 114-131.","targetRectangle":{"y":272.3076171875,"x":209,"width":774.76318359375,"height":34.00732421875}},{"text":"Coutand, I., Whipp, D. M., Grujic, D., Bernet, M., Fellin, M. G., Bookhagen, B., ... & Duncan, C. (2014). Geometry and kinematics of the Main Himalayan Thrust and Neogene crustal exhumation in the Bhutanese Himalaya derived from inversion of multithermochronologic data. Journal of Geophysical Research: Solid Earth, 119(2), 1446-1481.","targetRectangle":{"y":306.31494140625,"x":209,"width":770.19287109375,"height":51.00732421875}},{"text":"Currie, C. A., Ducea, M. N., DeCelles, P. G., & Beaumont, C. (2015). Geodynamic models of Cordilleran orogens: Gravitational instability of magmatic arc roots. Geological Society of America Memoirs, 212, 1-22.","targetRectangle":{"y":357.322265625,"x":209,"width":756.85546875,"height":34.00732421875}},{"text":"Gerya, T. (2010). Introduction to numerical geodynamic modelling. Cambridge University Press.","targetRectangle":{"y":391.32958984375,"x":209,"width":546.73828125,"height":17.00732421875}},{"text":"Gradmann, S., Ebbing, J., & Fullea, J. (2013). Integrated geophysical modelling of a lateral transition zone in the lithospheric mantle under Norway and Sweden. Geophysical Journal International, 194(3), 1359-1374.","targetRectangle":{"y":408.3369140625,"x":209,"width":778.60107421875,"height":34.00732421875}},{"text":"Jackson, J. (2002). Strength of the continental lithosphere: time to abandon the jelly sandwich?. GSA today, 12(9), 4-9.","targetRectangle":{"y":442.34423828125,"x":209,"width":695.54443359375,"height":17.00732421875}},{"text":"Lahtinen, R., Johnston, S. T., & Nironen, M. (2014). The Bothnian coupled oroclines of the Svecofennian Orogen: a Palaeoproterozoic terrane wreck. Terra Nova, 26(4), 330-335.","targetRectangle":{"y":459.3515625,"x":209,"width":678.720703125,"height":34.00732421875}},{"text":"Mosher, S., Levine, J. S. F., & Carlson, W. D. (2008). Mesoproterozoic plate tectonics: A collisional model for the Grenville-aged orogenic belt in the Llano uplift, central Texas. Geology, 36(1), 55-58.","targetRectangle":{"y":493.35888671875,"x":209,"width":754.57763671875,"height":34.00732421875}},{"text":"Rosenberg, C., Medvedev, S., & Handy, M. (2007). Effects of Melting on Faulting and Continental Deformation In M.R. Handy, G. Hirth, & N. Hovius (Ed.), Tectonic Faults: Agents of Change on a Dynamic Earth. Cambridge, MA: MIT Press.","targetRectangle":{"y":527.3662109375,"x":209,"width":762.9931640625,"height":34.00732421875}},{"text":"Skyttä, P., Bauer, T., Hermansson, T., Dehghannejad, M., Juhlin, C., García, M., ... & Weihed, P. (2013). Structural evolution of the VMS-hosting Kristineberg area, Sweden—constraints from structural analysis and 3-D-modelling. Solid Earth Discuss, 4, 1281-1315.","targetRectangle":{"y":561.37353515625,"x":209,"width":776.28662109375,"height":34.00732421875}},{"text":"Stüwe, K. (2007). Geodynamics of the lithosphere: an introduction. Springer Science & Business Media.","targetRectangle":{"y":595.380859375,"x":209,"width":589.21142578125,"height":17.00732421875}},{"text":"Tapponnier, P., Peltzer, G., Le Dain, A. Y., Armijo, R., & Cobbold, P. (1982). Propagating extrusion tectonics in Asia: new insights from simple experiments with plasticine. Geology, 10(12), 611-616.","targetRectangle":{"y":612.38818359375,"x":209,"width":782.38037109375,"height":34}},{"text":"Turcotte, D. L., & Schubert, G. (2014). Geodynamics (3rd ed.). Cambridge University Press.","targetRectangle":{"y":646.38818359375,"x":209,"width":536.220703125,"height":17.00732421875}},{"text":"Twiss, R. J., & Moores, E. M. (2007). Structural geology (2nd ed.). Macmillan.","targetRectangle":{"y":663.3955078125,"x":209,"width":436.728515625,"height":17.00732421875}},{"text":"Intro to geodynamic modelling","targetRectangle":{"y":720,"x":305.5211486816406,"width":173.3251953125,"height":16}}],"baseLayer":{"animations":[],"initialState":{"affineTransform":[1,0,0,1,0,0],"masksToBounds":false,"rotation":0,"scale":1,"position":{"pointX":512,"pointY":384},"width":1024,"sublayerTransform":[1,0,0,0,0,1,0,0,0,0,1,0,0,0,0,1],"contentsRect":{"y":0,"x":0,"width":1,"height":1},"opacity":1,"edgeAntialiasingMask":251658240,"height":768,"hidden":false,"anchorPoint":{"pointX":0.5,"pointY":0.5}},"objectID":"0","layers":[{"animations":[],"initialState":{"affineTransform":[1,0,0,1,0,0],"masksToBounds":false,"rotation":0,"scale":1,"position":{"pointX":512,"pointY":384},"width":1024,"sublayerTransform":[1,0,0,0,0,1,0,0,0,0,1,-0.0004922987690640373,0,0,0,1],"contentsRect":{"y":0,"x":0,"width":1,"height":1},"opacity":1,"edgeAntialiasingMask":251658240,"height":768,"hidden":false,"anchorPoint":{"pointX":0.5,"pointY":0.5}},"layers":[{"animations":[],"layers":[],"initialState":{"affineTransform":[1,0,0,1,0,0],"masksToBounds":false,"rotation":0,"scale":1,"position":{"pointX":512,"pointY":384},"width":1024,"sublayerTransform":[1,0,0,0,0,1,0,0,0,0,1,0,0,0,0,1],"contentsRect":{"y":0,"x":0,"width":1,"height":1},"opacity":1,"edgeAntialiasingMask":0,"height":768,"hidden":false,"anchorPoint":{"pointX":0.5,"pointY":0.5}},"texture":"BC61442EF858D1B1100978DBB6B7004F"}]}]}}]}