{"assets":{"F348D45C12914443FADACC82E31DDE22":{"type":"texture","index":134,"assetRequest":{"type":"slide","state":"outgoing","slide":"E1BC5E68-1695-49F3-8B4A-3177AD604B42"},"url":{"web":"assets/F348D45C12914443FADACC82E31DDE22.svg"},"width":1024,"height":768},"FAB039043D75907958D8E1CDF7416268":{"type":"texture","index":135,"assetRequest":{"type":"slide","state":"incoming","slide":"BF8138CC-14DA-41BE-B555-343A8EA40404"},"url":{"web":"assets/FAB039043D75907958D8E1CDF7416268.svg"},"width":1024,"height":768}},"events":[{"effects":[{"beginTime":0,"baseLayer":{"animations":[],"initialState":{"affineTransform":[1,0,0,1,0,0],"masksToBounds":false,"rotation":0,"scale":1,"position":{"pointX":512,"pointY":384},"width":1024,"sublayerTransform":[1,0,0,0,0,1,0,0,0,0,1,0,0,0,0,1],"contentsRect":{"y":0,"x":0,"width":1,"height":1},"opacity":1,"edgeAntialiasingMask":251658240,"height":768,"hidden":false,"anchorPoint":{"pointX":0.5,"pointY":0.5}},"objectID":"0","layers":[{"animations":[],"initialState":{"affineTransform":[1,0,0,1,0,0],"masksToBounds":false,"rotation":0,"scale":1,"position":{"pointX":512,"pointY":384},"width":1024,"sublayerTransform":[1,0,0,0,0,1,0,0,0,0,1,-0.0004922987690640373,0,0,0,1],"contentsRect":{"y":0,"x":0,"width":1,"height":1},"opacity":1,"edgeAntialiasingMask":251658240,"height":768,"hidden":false,"anchorPoint":{"pointX":0.5,"pointY":0.5}},"layers":[{"animations":[],"layers":[],"initialState":{"affineTransform":[1,0,0,1,0,0],"masksToBounds":false,"rotation":0,"scale":1,"position":{"pointX":512,"pointY":384},"width":1024,"sublayerTransform":[1,0,0,0,0,1,0,0,0,0,1,0,0,0,0,1],"contentsRect":{"y":0,"x":0,"width":1,"height":1},"opacity":1,"edgeAntialiasingMask":0,"height":768,"hidden":false,"anchorPoint":{"pointX":0.5,"pointY":0.5}},"texture":"FAB039043D75907958D8E1CDF7416268"},{"animations":[{"timeOffset":0,"from":{"scalar":false},"beginTime":0,"repeatCount":0,"fillMode":"both","property":"hidden","autoreverses":false,"duration":0.01,"to":{"scalar":true}}],"layers":[],"initialState":{"affineTransform":[1,0,0,1,0,0],"masksToBounds":false,"rotation":0,"scale":1,"position":{"pointX":512,"pointY":384},"width":1024,"sublayerTransform":[1,0,0,0,0,1,0,0,0,0,1,0,0,0,0,1],"contentsRect":{"y":0,"x":0,"width":1,"height":1},"opacity":1,"edgeAntialiasingMask":0,"height":768,"hidden":false,"anchorPoint":{"pointX":0.5,"pointY":0.5}},"texture":"F348D45C12914443FADACC82E31DDE22"}]}]},"effects":[],"duration":0.01,"type":"transition","name":"none","objectID":"0"}],"automaticPlay":false,"hyperlinks":[],"accessibility":[{"text":"basic_FoS_flame_logo.pdf","targetRectangle":{"y":-5,"x":-7,"width":215,"height":203.0555572509766}},{"text":"￼","targetRectangle":{"y":720,"x":972.5,"width":14,"height":16}},{"text":"www.helsinki.fi/yliopisto","targetRectangle":{"y":720,"x":611,"width":136.28125,"height":16}},{"text":"Body force: Forces that act throughout the volume of a solid. Proportional to its volume or mass.","targetRectangle":{"y":256,"x":278.9999985694885,"width":704.01953125,"height":89}},{"text":"Example: Slab pull (gravity)","targetRectangle":{"y":345,"x":313.9999985694885,"width":299.044921875,"height":56}},{"text":"Surface force: Forces that act on the surface area bounding an element or volume. Proportional to the area upon which the force acts.","targetRectangle":{"y":457,"x":278.9999985694885,"width":718.8125,"height":121}},{"text":"Example: Friction along a fault plane","targetRectangle":{"y":578,"x":313.9999985694885,"width":404.208984375,"height":32}},{"text":"Body forces versus surface forces","targetRectangle":{"y":68,"x":209,"width":636.5940000000002,"height":57}},{"text":"Intro to geodynamic modelling","targetRectangle":{"y":720,"x":305.5211486816406,"width":173.3251953125,"height":16}},{"text":"HY_mLC05_txt__L_3L_V4__CMYK.pdf","targetRectangle":{"y":677,"x":24,"width":200.0000152587891,"height":68.71165466308594}}],"baseLayer":{"animations":[],"initialState":{"affineTransform":[1,0,0,1,0,0],"masksToBounds":false,"rotation":0,"scale":1,"position":{"pointX":512,"pointY":384},"width":1024,"sublayerTransform":[1,0,0,0,0,1,0,0,0,0,1,0,0,0,0,1],"contentsRect":{"y":0,"x":0,"width":1,"height":1},"opacity":1,"edgeAntialiasingMask":251658240,"height":768,"hidden":false,"anchorPoint":{"pointX":0.5,"pointY":0.5}},"objectID":"0","layers":[{"animations":[],"initialState":{"affineTransform":[1,0,0,1,0,0],"masksToBounds":false,"rotation":0,"scale":1,"position":{"pointX":512,"pointY":384},"width":1024,"sublayerTransform":[1,0,0,0,0,1,0,0,0,0,1,-0.0004922987690640373,0,0,0,1],"contentsRect":{"y":0,"x":0,"width":1,"height":1},"opacity":1,"edgeAntialiasingMask":251658240,"height":768,"hidden":false,"anchorPoint":{"pointX":0.5,"pointY":0.5}},"layers":[{"animations":[],"layers":[],"initialState":{"affineTransform":[1,0,0,1,0,0],"masksToBounds":false,"rotation":0,"scale":1,"position":{"pointX":512,"pointY":384},"width":1024,"sublayerTransform":[1,0,0,0,0,1,0,0,0,0,1,0,0,0,0,1],"contentsRect":{"y":0,"x":0,"width":1,"height":1},"opacity":1,"edgeAntialiasingMask":0,"height":768,"hidden":false,"anchorPoint":{"pointX":0.5,"pointY":0.5}},"texture":"F348D45C12914443FADACC82E31DDE22"}]}]}}]}